claimer/__init__.py
claimer/paragraph.py
claimer/parser.py
claimer-0.0.3.dist-info/LICENSE
claimer-0.0.3.dist-info/METADATA
claimer-0.0.3.dist-info/WHEEL
claimer-0.0.3.dist-info/top_level.txt
claimer-0.0.3.dist-info/RECORD
