Metadata-Version: 2.1
Name: claimer
Version: 0.0.3
Summary: Breaks down a textual paragraph into verifiable claims.
Author-email: Carlos Badenes-Olmedo <carlos.badenes@upm.es>
Project-URL: Homepage, https://github.com/librairy/claimer
Project-URL: Bug Tracker, https://github.com/librairy/claimer/issues
Classifier: Programming Language :: Python :: 3
Classifier: License :: OSI Approved :: Apache Software License
Classifier: Operating System :: OS Independent
Classifier: Topic :: Internet :: WWW/HTTP :: Indexing/Search
Classifier: Natural Language :: English
Classifier: Topic :: Software Development :: Libraries
Requires-Python: >=3.7
License-File: LICENSE
Requires-Dist: fastcoref
Requires-Dist: spacy
Requires-Dist: spacy-entity-linker
